tinkaf/__init__.py
tinkaf-0.0.0.dist-info/LICENSE
tinkaf-0.0.0.dist-info/METADATA
tinkaf-0.0.0.dist-info/WHEEL
tinkaf-0.0.0.dist-info/top_level.txt
tinkaf-0.0.0.dist-info/RECORD
