Metadata-Version: 2.1
Name: tinkaf
Version: 0.0.0
Summary: TINKoff Algotrading Framework
Home-page: https://github.com/0dminnimda/Tinkoff-Algotrading-Framework
Author: 0dminnimda
Author-email: 0dminnimda.contact@gmail.com
License: Apache-2.0
Project-URL: Bug tracker, https://github.com/0dminnimda/Tinkoff-Algotrading-Framework/issues
Platform: UNKNOWN
Classifier: Development Status :: 1 - Planning
Classifier: Intended Audience :: Developers
Classifier: Intended Audience :: Financial and Insurance Industry
Classifier: License :: OSI Approved :: Apache Software License
Classifier: Programming Language :: Python
Classifier: Programming Language :: Python :: 3
Classifier: Programming Language :: Python :: 3 :: Only
Classifier: Programming Language :: Python :: 3.8
Classifier: Programming Language :: Python :: 3.9
Classifier: Programming Language :: Python :: 3.10
Classifier: Topic :: Software Development :: Libraries :: Python Modules
Classifier: Topic :: Office/Business :: Financial
Classifier: Topic :: Office/Business :: Financial :: Investment
Classifier: Topic :: Utilities
Classifier: Typing :: Typed
Requires-Python: >=3.8
License-File: LICENSE
